{"data":[{"country_name":"Central African Republic","iso3":"CAF","series_name":"People using safely managed drinking water services (% of population)","series_code":"SH.H2O.SMDW.ZS","year":2024,"value":6.21748769},{"country_name":"Chad","iso3":"TCD","series_name":"People using safely managed drinking water services (% of population)","series_code":"SH.H2O.SMDW.ZS","year":2024,"value":6.340826474},{"country_name":"Tuvalu","iso3":"TUV","series_name":"People using safely managed drinking water services (% of population)","series_code":"SH.H2O.SMDW.ZS","year":2024,"value":8.722550433},{"country_name":"Sierra Leone","iso3":"SLE","series_name":"People using safely managed drinking water services (% of population)","series_code":"SH.H2O.SMDW.ZS","year":2024,"value":10.8953836},{"country_name":"Congo, Dem. Rep.","iso3":"COD","series_name":"People using safely managed drinking water services (% of population)","series_code":"SH.H2O.SMDW.ZS","year":2024,"value":11.87264818},{"country_name":"Ethiopia","iso3":"ETH","series_name":"People using safely managed drinking water services (% of population)","series_code":"SH.H2O.SMDW.ZS","year":2024,"value":13.54720092},{"country_name":"Kiribati","iso3":"KIR","series_name":"People using safely managed drinking water services (% of population)","series_code":"SH.H2O.SMDW.ZS","year":2024,"value":15.0879416},{"country_name":"Nepal","iso3":"NPL","series_name":"People using safely managed drinking water services (% of population)","series_code":"SH.H2O.SMDW.ZS","year":2024,"value":16.48688567},{"country_name":"Benin","iso3":"BEN","series_name":"People using safely managed drinking water services (% of population)","series_code":"SH.H2O.SMDW.ZS","year":2024,"value":17.69683224},{"country_name":"Uganda","iso3":"UGA","series_name":"People using safely managed drinking water services (% of population)","series_code":"SH.H2O.SMDW.ZS","year":2024,"value":18.09712278},{"country_name":"Malawi","iso3":"MWI","series_name":"People using safely managed drinking water services (% of population)","series_code":"SH.H2O.SMDW.ZS","year":2024,"value":18.18165397},{"country_name":"Nauru","iso3":"NRU","series_name":"People using safely managed drinking water services (% of population)","series_code":"SH.H2O.SMDW.ZS","year":2024,"value":18.66316211},{"country_name":"Vanuatu","iso3":"VUT","series_name":"People using safely managed drinking water services (% of population)","series_code":"SH.H2O.SMDW.ZS","year":2024,"value":19.19708399},{"country_name":"Togo","iso3":"TGO","series_name":"People using safely managed drinking water services (% of population)","series_code":"SH.H2O.SMDW.ZS","year":2024,"value":20.52323528},{"country_name":"Madagascar","iso3":"MDG","series_name":"People using safely managed drinking water services (% of population)","series_code":"SH.H2O.SMDW.ZS","year":2024,"value":22.05599449},{"country_name":"Guinea-Bissau","iso3":"GNB","series_name":"People using safely managed drinking water services (% of population)","series_code":"SH.H2O.SMDW.ZS","year":2024,"value":23.98501679},{"country_name":"Zimbabwe","iso3":"ZWE","series_name":"People using safely managed drinking water services (% of population)","series_code":"SH.H2O.SMDW.ZS","year":2024,"value":25.46056336},{"country_name":"Senegal","iso3":"SEN","series_name":"People using safely managed drinking water services (% of population)","series_code":"SH.H2O.SMDW.ZS","year":2024,"value":27.19314071},{"country_name":"Mozambique","iso3":"MOZ","series_name":"People using safely managed drinking water services (% of population)","series_code":"SH.H2O.SMDW.ZS","year":2024,"value":27.5429457},{"country_name":"Tonga","iso3":"TON","series_name":"People using safely managed drinking water services (% of population)","series_code":"SH.H2O.SMDW.ZS","year":2024,"value":29.59845432},{"country_name":"Nigeria","iso3":"NGA","series_name":"People using safely managed drinking water services (% of population)","series_code":"SH.H2O.SMDW.ZS","year":2024,"value":29.90459919},{"country_name":"Cambodia","iso3":"KHM","series_name":"People using safely managed drinking water services (% of population)","series_code":"SH.H2O.SMDW.ZS","year":2024,"value":29.98557614},{"country_name":"Indonesia","iso3":"IDN","series_name":"People using safely managed drinking water services (% of population)","series_code":"SH.H2O.SMDW.ZS","year":2024,"value":30.46097736},{"country_name":"Afghanistan","iso3":"AFG","series_name":"People using safely managed drinking water services (% of population)","series_code":"SH.H2O.SMDW.ZS","year":2024,"value":30.55472231},{"country_name":"Lesotho","iso3":"LSO","series_name":"People using safely managed drinking water services (% of population)","series_code":"SH.H2O.SMDW.ZS","year":2024,"value":31.32024171},{"country_name":"Tanzania","iso3":"TZA","series_name":"People using safely managed drinking water services (% of population)","series_code":"SH.H2O.SMDW.ZS","year":2024,"value":31.32539895},{"country_name":"Lao PDR","iso3":"LAO","series_name":"People using safely managed drinking water services (% of population)","series_code":"SH.H2O.SMDW.ZS","year":2024,"value":35.18772308},{"country_name":"Cote d'Ivoire","iso3":"CIV","series_name":"People using safely managed drinking water services (% of population)","series_code":"SH.H2O.SMDW.ZS","year":2024,"value":36.44893816},{"country_name":"Sao Tome and Principe","iso3":"STP","series_name":"People using safely managed drinking water services (% of population)","series_code":"SH.H2O.SMDW.ZS","year":2024,"value":36.68003809},{"country_name":"Eswatini","iso3":"SWZ","series_name":"People using safely managed drinking water services (% of population)","series_code":"SH.H2O.SMDW.ZS","year":2024,"value":38.2165357},{"country_name":"Fiji","iso3":"FJI","series_name":"People using safely managed drinking water services (% of population)","series_code":"SH.H2O.SMDW.ZS","year":2024,"value":42.11075011},{"country_name":"Ghana","iso3":"GHA","series_name":"People using safely managed drinking water services (% of population)","series_code":"SH.H2O.SMDW.ZS","year":2024,"value":42.9413892},{"country_name":"Mexico","iso3":"MEX","series_name":"People using safely managed drinking water services (% of population)","series_code":"SH.H2O.SMDW.ZS","year":2024,"value":42.96663115},{"country_name":"Mongolia","iso3":"MNG","series_name":"People using safely managed drinking water services (% of population)","series_code":"SH.H2O.SMDW.ZS","year":2024,"value":43.3607223},{"country_name":"Pakistan","iso3":"PAK","series_name":"People using safely managed drinking water services (% of population)","series_code":"SH.H2O.SMDW.ZS","year":2024,"value":44.97373641},{"country_name":"Dominican Republic","iso3":"DOM","series_name":"People using safely managed drinking water services (% of population)","series_code":"SH.H2O.SMDW.ZS","year":2024,"value":45.33240707},{"country_name":"Sri Lanka","iso3":"LKA","series_name":"People using safely managed drinking water services (% of population)","series_code":"SH.H2O.SMDW.ZS","year":2024,"value":46.93297051},{"country_name":"Turks and Caicos Islands","iso3":"TCA","series_name":"People using safely managed drinking water services (% of population)","series_code":"SH.H2O.SMDW.ZS","year":2024,"value":47.04991877},{"country_name":"Lebanon","iso3":"LBN","series_name":"People using safely managed drinking water services (% of population)","series_code":"SH.H2O.SMDW.ZS","year":2024,"value":47.7},{"country_name":"Gambia, The","iso3":"GMB","series_name":"People using safely managed drinking water services (% of population)","series_code":"SH.H2O.SMDW.ZS","year":2024,"value":48.17900349},{"country_name":"Philippines","iso3":"PHL","series_name":"People using safely managed drinking water services (% of population)","series_code":"SH.H2O.SMDW.ZS","year":2024,"value":48.48405774},{"country_name":"Guatemala","iso3":"GTM","series_name":"People using safely managed drinking water services (% of population)","series_code":"SH.H2O.SMDW.ZS","year":2024,"value":48.78719507},{"country_name":"Peru","iso3":"PER","series_name":"People using safely managed drinking water services (% of population)","series_code":"SH.H2O.SMDW.ZS","year":2024,"value":49.42839623},{"country_name":"Suriname","iso3":"SUR","series_name":"People using safely managed drinking water services (% of population)","series_code":"SH.H2O.SMDW.ZS","year":2024,"value":55.84724104},{"country_name":"Azerbaijan","iso3":"AZE","series_name":"People using safely managed drinking water services (% of population)","series_code":"SH.H2O.SMDW.ZS","year":2024,"value":57.81182832},{"country_name":"Viet Nam","iso3":"VNM","series_name":"People using safely managed drinking water services (% of population)","series_code":"SH.H2O.SMDW.ZS","year":2024,"value":58.58083914},{"country_name":"Bangladesh","iso3":"BGD","series_name":"People using safely managed drinking water services (% of population)","series_code":"SH.H2O.SMDW.ZS","year":2024,"value":59.12542599},{"country_name":"Myanmar","iso3":"MMR","series_name":"People using safely managed drinking water services (% of population)","series_code":"SH.H2O.SMDW.ZS","year":2024,"value":59.72397508},{"country_name":"Iraq","iso3":"IRQ","series_name":"People using safely managed drinking water services (% of population)","series_code":"SH.H2O.SMDW.ZS","year":2024,"value":59.82724613},{"country_name":"Samoa","iso3":"WSM","series_name":"People using safely managed drinking water services (% of population)","series_code":"SH.H2O.SMDW.ZS","year":2024,"value":62.5019406},{"country_name":"Botswana","iso3":"BWA","series_name":"People using safely managed drinking water services (% of population)","series_code":"SH.H2O.SMDW.ZS","year":2024,"value":63.29104124},{"country_name":"Paraguay","iso3":"PRY","series_name":"People using safely managed drinking water services (% of population)","series_code":"SH.H2O.SMDW.ZS","year":2024,"value":64.36471974},{"country_name":"Seychelles","iso3":"SYC","series_name":"People using safely managed drinking water services (% of population)","series_code":"SH.H2O.SMDW.ZS","year":2024,"value":64.70223163},{"country_name":"Tunisia","iso3":"TUN","series_name":"People using safely managed drinking water services (% of population)","series_code":"SH.H2O.SMDW.ZS","year":2024,"value":64.97810721},{"country_name":"Tajikistan","iso3":"TJK","series_name":"People using safely managed drinking water services (% of population)","series_code":"SH.H2O.SMDW.ZS","year":2024,"value":65.10807152},{"country_name":"Honduras","iso3":"HND","series_name":"People using safely managed drinking water services (% of population)","series_code":"SH.H2O.SMDW.ZS","year":2024,"value":65.51622118},{"country_name":"Bhutan","iso3":"BTN","series_name":"People using safely managed drinking water services (% of population)","series_code":"SH.H2O.SMDW.ZS","year":2024,"value":65.59421597},{"country_name":"Guyana","iso3":"GUY","series_name":"People using safely managed drinking water services (% of population)","series_code":"SH.H2O.SMDW.ZS","year":2024,"value":67.17443743},{"country_name":"South Africa","iso3":"ZAF","series_name":"People using safely managed drinking water services (% of population)","series_code":"SH.H2O.SMDW.ZS","year":2024,"value":68.00756388},{"country_name":"Algeria","iso3":"DZA","series_name":"People using safely managed drinking water services (% of population)","series_code":"SH.H2O.SMDW.ZS","year":2024,"value":69.02918252},{"country_name":"Trinidad and Tobago","iso3":"TTO","series_name":"People using safely managed drinking water services (% of population)","series_code":"SH.H2O.SMDW.ZS","year":2024,"value":69.36926267},{"country_name":"Ecuador","iso3":"ECU","series_name":"People using safely managed drinking water services (% of population)","series_code":"SH.H2O.SMDW.ZS","year":2024,"value":69.8869997},{"country_name":"Georgia","iso3":"GEO","series_name":"People using safely managed drinking water services (% of population)","series_code":"SH.H2O.SMDW.ZS","year":2024,"value":70.52660973},{"country_name":"Albania","iso3":"ALB","series_name":"People using safely managed drinking water services (% of population)","series_code":"SH.H2O.SMDW.ZS","year":2024,"value":70.79373639},{"country_name":"Kyrgyz Republic","iso3":"KGZ","series_name":"People using safely managed drinking water services (% of population)","series_code":"SH.H2O.SMDW.ZS","year":2024,"value":73.8812993},{"country_name":"Colombia","iso3":"COL","series_name":"People using safely managed drinking water services (% of population)","series_code":"SH.H2O.SMDW.ZS","year":2024,"value":74.33929919},{"country_name":"Serbia","iso3":"SRB","series_name":"People using safely managed drinking water services (% of population)","series_code":"SH.H2O.SMDW.ZS","year":2024,"value":74.96726348},{"country_name":"Moldova","iso3":"MDA","series_name":"People using safely managed drinking water services (% of population)","series_code":"SH.H2O.SMDW.ZS","year":2024,"value":75.81589087},{"country_name":"Russian Federation","iso3":"RUS","series_name":"People using safely managed drinking water services (% of population)","series_code":"SH.H2O.SMDW.ZS","year":2024,"value":76.26072942},{"country_name":"India","iso3":"IND","series_name":"People using safely managed drinking water services (% of population)","series_code":"SH.H2O.SMDW.ZS","year":2024,"value":76.44219421},{"country_name":"Egypt, Arab Rep.","iso3":"EGY","series_name":"People using safely managed drinking water services (% of population)","series_code":"SH.H2O.SMDW.ZS","year":2024,"value":78.94015883},{"country_name":"Morocco","iso3":"MAR","series_name":"People using safely managed drinking water services (% of population)","series_code":"SH.H2O.SMDW.ZS","year":2024,"value":79.98180723},{"country_name":"Costa Rica","iso3":"CRI","series_name":"People using safely managed drinking water services (% of population)","series_code":"SH.H2O.SMDW.ZS","year":2024,"value":80.50007424},{"country_name":"West Bank and Gaza","iso3":"PSE","series_name":"People using safely managed drinking water services (% of population)","series_code":"SH.H2O.SMDW.ZS","year":2024,"value":80.6420172},{"country_name":"North Macedonia","iso3":"MKD","series_name":"People using safely managed drinking water services (% of population)","series_code":"SH.H2O.SMDW.ZS","year":2024,"value":80.79054149},{"country_name":"Northern Mariana Islands","iso3":"MNP","series_name":"People using safely managed drinking water services (% of population)","series_code":"SH.H2O.SMDW.ZS","year":2024,"value":81.45454545},{"country_name":"Uzbekistan","iso3":"UZB","series_name":"People using safely managed drinking water services (% of population)","series_code":"SH.H2O.SMDW.ZS","year":2024,"value":81.9295048},{"country_name":"Armenia","iso3":"ARM","series_name":"People using safely managed drinking water services (% of population)","series_code":"SH.H2O.SMDW.ZS","year":2024,"value":82.07281919},{"country_name":"Romania","iso3":"ROU","series_name":"People using safely managed drinking water services (% of population)","series_code":"SH.H2O.SMDW.ZS","year":2024,"value":82.18299294},{"country_name":"Montenegro","iso3":"MNE","series_name":"People using safely managed drinking water services (% of population)","series_code":"SH.H2O.SMDW.ZS","year":2024,"value":85.50091179},{"country_name":"Bosnia and Herzegovina","iso3":"BIH","series_name":"People using safely managed drinking water services (% of population)","series_code":"SH.H2O.SMDW.ZS","year":2024,"value":86.40010788},{"country_name":"Croatia","iso3":"HRV","series_name":"People using safely managed drinking water services (% of population)","series_code":"SH.H2O.SMDW.ZS","year":2024,"value":87.26826925},{"country_name":"Ukraine","iso3":"UKR","series_name":"People using safely managed drinking water services (% of population)","series_code":"SH.H2O.SMDW.ZS","year":2024,"value":87.86837694},{"country_name":"Brazil","iso3":"BRA","series_name":"People using safely managed drinking water services (% of population)","series_code":"SH.H2O.SMDW.ZS","year":2024,"value":88.62396607},{"country_name":"Poland","iso3":"POL","series_name":"People using safely managed drinking water services (% of population)","series_code":"SH.H2O.SMDW.ZS","year":2024,"value":88.67554625},{"country_name":"Jordan","iso3":"JOR","series_name":"People using safely managed drinking water services (% of population)","series_code":"SH.H2O.SMDW.ZS","year":2024,"value":88.95029853},{"country_name":"French Polynesia","iso3":"PYF","series_name":"People using safely managed drinking water services (% of population)","series_code":"SH.H2O.SMDW.ZS","year":2024,"value":90.44871795},{"country_name":"American Samoa","iso3":"ASM","series_name":"People using safely managed drinking water services (% of population)","series_code":"SH.H2O.SMDW.ZS","year":2024,"value":90.53833605},{"country_name":"Andorra","iso3":"AND","series_name":"People using safely managed drinking water services (% of population)","series_code":"SH.H2O.SMDW.ZS","year":2024,"value":90.64000181},{"country_name":"Palau","iso3":"PLW","series_name":"People using safely managed drinking water services (% of population)","series_code":"SH.H2O.SMDW.ZS","year":2024,"value":90.77521735},{"country_name":"Oman","iso3":"OMN","series_name":"People using safely managed drinking water services (% of population)","series_code":"SH.H2O.SMDW.ZS","year":2024,"value":91.10117441},{"country_name":"Kazakhstan","iso3":"KAZ","series_name":"People using safely managed drinking water services (% of population)","series_code":"SH.H2O.SMDW.ZS","year":2024,"value":91.54541823},{"country_name":"Belarus","iso3":"BLR","series_name":"People using safely managed drinking water services (% of population)","series_code":"SH.H2O.SMDW.ZS","year":2024,"value":93.05975529},{"country_name":"Guam","iso3":"GUM","series_name":"People using safely managed drinking water services (% of population)","series_code":"SH.H2O.SMDW.ZS","year":2024,"value":93.99715378},{"country_name":"Iran, Islamic Rep.","iso3":"IRN","series_name":"People using safely managed drinking water services (% of population)","series_code":"SH.H2O.SMDW.ZS","year":2024,"value":94.41220521},{"country_name":"Malaysia","iso3":"MYS","series_name":"People using safely managed drinking water services (% of population)","series_code":"SH.H2O.SMDW.ZS","year":2024,"value":94.70036186},{"country_name":"Turkmenistan","iso3":"TKM","series_name":"People using safely managed drinking water services (% of population)","series_code":"SH.H2O.SMDW.ZS","year":2024,"value":94.85354592},{"country_name":"Portugal","iso3":"PRT","series_name":"People using safely managed drinking water services (% of population)","series_code":"SH.H2O.SMDW.ZS","year":2024,"value":95.21734795},{"country_name":"Qatar","iso3":"QAT","series_name":"People using safely managed drinking water services (% of population)","series_code":"SH.H2O.SMDW.ZS","year":2024,"value":95.34524188},{"country_name":"Ireland","iso3":"IRL","series_name":"People using safely managed drinking water services (% of population)","series_code":"SH.H2O.SMDW.ZS","year":2024,"value":96.12501116},{"country_name":"Bulgaria","iso3":"BGR","series_name":"People using safely managed drinking water services (% of population)","series_code":"SH.H2O.SMDW.ZS","year":2024,"value":96.20707815},{"country_name":"St. Martin (French part)","iso3":"MAF","series_name":"People using safely managed drinking water services (% of population)","series_code":"SH.H2O.SMDW.ZS","year":2024,"value":96.62548146},{"country_name":"Greece","iso3":"GRC","series_name":"People using safely managed drinking water services (% of population)","series_code":"SH.H2O.SMDW.ZS","year":2024,"value":96.68615548},{"country_name":"Switzerland","iso3":"CHE","series_name":"People using safely managed drinking water services (% of population)","series_code":"SH.H2O.SMDW.ZS","year":2024,"value":96.69999689},{"country_name":"Lithuania","iso3":"LTU","series_name":"People using safely managed drinking water services (% of population)","series_code":"SH.H2O.SMDW.ZS","year":2024,"value":96.73357426},{"country_name":"Italy","iso3":"ITA","series_name":"People using safely managed drinking water services (% of population)","series_code":"SH.H2O.SMDW.ZS","year":2024,"value":96.75843583},{"country_name":"New Caledonia","iso3":"NCL","series_name":"People using safely managed drinking water services (% of population)","series_code":"SH.H2O.SMDW.ZS","year":2024,"value":96.86528541},{"country_name":"Canada","iso3":"CAN","series_name":"People using safely managed drinking water services (% of population)","series_code":"SH.H2O.SMDW.ZS","year":2024,"value":96.89032266},{"country_name":"Latvia","iso3":"LVA","series_name":"People using safely managed drinking water services (% of population)","series_code":"SH.H2O.SMDW.ZS","year":2024,"value":97.01140687},{"country_name":"United States","iso3":"USA","series_name":"People using safely managed drinking water services (% of population)","series_code":"SH.H2O.SMDW.ZS","year":2024,"value":97.56768844},{"country_name":"Chile","iso3":"CHL","series_name":"People using safely managed drinking water services (% of population)","series_code":"SH.H2O.SMDW.ZS","year":2024,"value":97.8170552},{"country_name":"Czechia","iso3":"CZE","series_name":"People using safely managed drinking water services (% of population)","series_code":"SH.H2O.SMDW.ZS","year":2024,"value":98.14487284},{"country_name":"United Arab Emirates","iso3":"ARE","series_name":"People using safely managed drinking water services (% of population)","series_code":"SH.H2O.SMDW.ZS","year":2024,"value":98.64131723},{"country_name":"Virgin Islands (U.S.)","iso3":"VIR","series_name":"People using safely managed drinking water services (% of population)","series_code":"SH.H2O.SMDW.ZS","year":2024,"value":98.67748374},{"country_name":"Japan","iso3":"JPN","series_name":"People using safely managed drinking water services (% of population)","series_code":"SH.H2O.SMDW.ZS","year":2024,"value":98.72702421},{"country_name":"Austria","iso3":"AUT","series_name":"People using safely managed drinking water services (% of population)","series_code":"SH.H2O.SMDW.ZS","year":2024,"value":98.89153572},{"country_name":"Bahrain","iso3":"BHR","series_name":"People using safely managed drinking water services (% of population)","series_code":"SH.H2O.SMDW.ZS","year":2024,"value":98.90397556},{"country_name":"Puerto Rico (US)","iso3":"PRI","series_name":"People using safely managed drinking water services (% of population)","series_code":"SH.H2O.SMDW.ZS","year":2024,"value":98.94026184},{"country_name":"Estonia","iso3":"EST","series_name":"People using safely managed drinking water services (% of population)","series_code":"SH.H2O.SMDW.ZS","year":2024,"value":98.94390973},{"country_name":"Norway","iso3":"NOR","series_name":"People using safely managed drinking water services (% of population)","series_code":"SH.H2O.SMDW.ZS","year":2024,"value":99.06248306},{"country_name":"Korea, Rep.","iso3":"KOR","series_name":"People using safely managed drinking water services (% of population)","series_code":"SH.H2O.SMDW.ZS","year":2024,"value":99.28266946},{"country_name":"Spain","iso3":"ESP","series_name":"People using safely managed drinking water services (% of population)","series_code":"SH.H2O.SMDW.ZS","year":2024,"value":99.45846467},{"country_name":"Israel","iso3":"ISR","series_name":"People using safely managed drinking water services (% of population)","series_code":"SH.H2O.SMDW.ZS","year":2024,"value":99.46198769},{"country_name":"Belgium","iso3":"BEL","series_name":"People using safely managed drinking water services (% of population)","series_code":"SH.H2O.SMDW.ZS","year":2024,"value":99.54713452},{"country_name":"Slovak Republic","iso3":"SVK","series_name":"People using safely managed drinking water services (% of population)","series_code":"SH.H2O.SMDW.ZS","year":2024,"value":99.57155691},{"country_name":"Slovenia","iso3":"SVN","series_name":"People using safely managed drinking water services (% of population)","series_code":"SH.H2O.SMDW.ZS","year":2024,"value":99.5745942},{"country_name":"Finland","iso3":"FIN","series_name":"People using safely managed drinking water services (% of population)","series_code":"SH.H2O.SMDW.ZS","year":2024,"value":99.64679671},{"country_name":"Luxembourg","iso3":"LUX","series_name":"People using safely managed drinking water services (% of population)","series_code":"SH.H2O.SMDW.ZS","year":2024,"value":99.65305502},{"country_name":"France","iso3":"FRA","series_name":"People using safely managed drinking water services (% of population)","series_code":"SH.H2O.SMDW.ZS","year":2024,"value":99.71270147},{"country_name":"Cyprus","iso3":"CYP","series_name":"People using safely managed drinking water services (% of population)","series_code":"SH.H2O.SMDW.ZS","year":2024,"value":99.72110883},{"country_name":"Sweden","iso3":"SWE","series_name":"People using safely managed drinking water services (% of population)","series_code":"SH.H2O.SMDW.ZS","year":2024,"value":99.76079667},{"country_name":"United Kingdom","iso3":"GBR","series_name":"People using safely managed drinking water services (% of population)","series_code":"SH.H2O.SMDW.ZS","year":2024,"value":99.82295068},{"country_name":"Malta","iso3":"MLT","series_name":"People using safely managed drinking water services (% of population)","series_code":"SH.H2O.SMDW.ZS","year":2024,"value":99.82676853},{"country_name":"Isle of Man","iso3":"IMN","series_name":"People using safely managed drinking water services (% of population)","series_code":"SH.H2O.SMDW.ZS","year":2024,"value":99.91059649},{"country_name":"Germany","iso3":"DEU","series_name":"People using safely managed drinking water services (% of population)","series_code":"SH.H2O.SMDW.ZS","year":2024,"value":99.91729795},{"country_name":"Denmark","iso3":"DNK","series_name":"People using safely managed drinking water services (% of population)","series_code":"SH.H2O.SMDW.ZS","year":2024,"value":99.91882714},{"country_name":"Netherlands","iso3":"NLD","series_name":"People using safely managed drinking water services (% of population)","series_code":"SH.H2O.SMDW.ZS","year":2024,"value":99.9595064},{"country_name":"San Marino","iso3":"SMR","series_name":"People using safely managed drinking water services (% of population)","series_code":"SH.H2O.SMDW.ZS","year":2024,"value":99.99999618},{"country_name":"New Zealand","iso3":"NZL","series_name":"People using safely managed drinking water services (% of population)","series_code":"SH.H2O.SMDW.ZS","year":2024,"value":100},{"country_name":"Macao SAR, China","iso3":"MAC","series_name":"People using safely managed drinking water services (% of population)","series_code":"SH.H2O.SMDW.ZS","year":2024,"value":100},{"country_name":"Monaco","iso3":"MCO","series_name":"People using safely managed drinking water services (% of population)","series_code":"SH.H2O.SMDW.ZS","year":2024,"value":100},{"country_name":"Singapore","iso3":"SGP","series_name":"People using safely managed drinking water services (% of population)","series_code":"SH.H2O.SMDW.ZS","year":2024,"value":100},{"country_name":"Liechtenstein","iso3":"LIE","series_name":"People using safely managed drinking water services (% of population)","series_code":"SH.H2O.SMDW.ZS","year":2024,"value":100},{"country_name":"Kuwait","iso3":"KWT","series_name":"People using safely managed drinking water services (% of population)","series_code":"SH.H2O.SMDW.ZS","year":2024,"value":100},{"country_name":"Iceland","iso3":"ISL","series_name":"People using safely managed drinking water services (% of population)","series_code":"SH.H2O.SMDW.ZS","year":2024,"value":100},{"country_name":"Hungary","iso3":"HUN","series_name":"People using safely managed drinking water services (% of population)","series_code":"SH.H2O.SMDW.ZS","year":2024,"value":100},{"country_name":"Hong Kong SAR, China","iso3":"HKG","series_name":"People using safely managed drinking water services (% of population)","series_code":"SH.H2O.SMDW.ZS","year":2024,"value":100},{"country_name":"Gibraltar","iso3":"GIB","series_name":"People using safely managed drinking water services (% of population)","series_code":"SH.H2O.SMDW.ZS","year":2024,"value":100}]}